{
  "project": {
    "pz": {
      "enr": {
        "1": {
          "cap": 10
        }
      },
      "sig": {
        "gorgeousCampaign": {
          "str": 10,
          "cap": 100,
          "dur": "s",
          "crit": {
            "op": "&",
            "type": "G",
            "clauses": [
              {
                "type": "QS",
                "match": {
                  "op": "*"
                },
                "queryName": "gclid"
              },
              {
                "type": "QS",
                "match": {
                  "cs": false,
                  "op": "=",
                  "rhs": "hello_gorgeous"
                },
                "queryName": "mycampaign"
              }
            ]
          }
        },
        "buttonIsDemo": {
          "str": 10,
          "cap": 50,
          "dur": "s",
          "crit": {
            "op": "&",
            "type": "G",
            "clauses": [
              {
                "type": "QS",
                "match": {
                  "cs": false,
                  "op": "=",
                  "rhs": "demo"
                },
                "queryName": "button"
              }
            ]
          }
        },
        "buttonIsDumb": {
          "str": 10,
          "cap": 50,
          "dur": "s",
          "crit": {
            "op": "&",
            "type": "G",
            "clauses": [
              {
                "type": "QS",
                "match": {
                  "cs": false,
                  "op": "=",
                  "rhs": "dumb"
                },
                "queryName": "button"
              }
            ]
          }
        }
      }
    },
    "test": {}
  }
}